tkaria11y/__init__.py
tkaria11y/a11y_engine.py
tkaria11y/app.py
tkaria11y/mixins.py
tkaria11y/utils.py
tkaria11y/widgets.py
tkaria11y/stubs/widgets.py
tkaria11y-0.0.1.dist-info/licenses/LICENSE
tkaria11y-0.0.1.dist-info/METADATA
tkaria11y-0.0.1.dist-info/WHEEL
tkaria11y-0.0.1.dist-info/entry_points.txt
tkaria11y-0.0.1.dist-info/top_level.txt
tkaria11y-0.0.1.dist-info/RECORD
