Metadata-Version: 2.4
Name: tkaria11y
Version: 0.0.1
Summary: ARIA-style, TTS-driven accessibility layer for the Tk ecosystem
Author-email: Stan Griffiths <stantgriffiths@gmail.com>
License: MIT
Keywords: tkinter,ttk,accessibility,a11y,tts,aria
Classifier: Programming Language :: Python :: 3
Classifier: License :: OSI Approved :: MIT License
Classifier: Operating System :: OS Independent
License-File: LICENSE
Requires-Dist: pyttsx3
Provides-Extra: dev
Requires-Dist: pytest; extra == "dev"
Requires-Dist: libcst; extra == "dev"
Requires-Dist: mypy; extra == "dev"
Requires-Dist: flake8; extra == "dev"
Requires-Dist: black; extra == "dev"
Requires-Dist: mkdocs; extra == "dev"
Dynamic: license-file
